tron_sdk_py/.DS_Store
tron_sdk_py/__init__.py
tron_sdk_py/client.py
tron_sdk_py/crypto.py
tron_sdk_py/keys.py
tron_sdk_py/proto/api/api_pb2.py
tron_sdk_py/proto/api/api_pb2_grpc.py
tron_sdk_py/proto/api/zksnark_pb2.py
tron_sdk_py/proto/api/zksnark_pb2_grpc.py
tron_sdk_py/proto/core/Discover_pb2.py
tron_sdk_py/proto/core/Discover_pb2_grpc.py
tron_sdk_py/proto/core/TronInventoryItems_pb2.py
tron_sdk_py/proto/core/TronInventoryItems_pb2_grpc.py
tron_sdk_py/proto/core/Tron_pb2.py
tron_sdk_py/proto/core/Tron_pb2_grpc.py
tron_sdk_py/proto/core/contract/account_contract_pb2.py
tron_sdk_py/proto/core/contract/account_contract_pb2_grpc.py
tron_sdk_py/proto/core/contract/asset_issue_contract_pb2.py
tron_sdk_py/proto/core/contract/asset_issue_contract_pb2_grpc.py
tron_sdk_py/proto/core/contract/balance_contract_pb2.py
tron_sdk_py/proto/core/contract/balance_contract_pb2_grpc.py
tron_sdk_py/proto/core/contract/common_pb2.py
tron_sdk_py/proto/core/contract/common_pb2_grpc.py
tron_sdk_py/proto/core/contract/exchange_contract_pb2.py
tron_sdk_py/proto/core/contract/exchange_contract_pb2_grpc.py
tron_sdk_py/proto/core/contract/market_contract_pb2.py
tron_sdk_py/proto/core/contract/market_contract_pb2_grpc.py
tron_sdk_py/proto/core/contract/proposal_contract_pb2.py
tron_sdk_py/proto/core/contract/proposal_contract_pb2_grpc.py
tron_sdk_py/proto/core/contract/shield_contract_pb2.py
tron_sdk_py/proto/core/contract/shield_contract_pb2_grpc.py
tron_sdk_py/proto/core/contract/smart_contract_pb2.py
tron_sdk_py/proto/core/contract/smart_contract_pb2_grpc.py
tron_sdk_py/proto/core/contract/storage_contract_pb2.py
tron_sdk_py/proto/core/contract/storage_contract_pb2_grpc.py
tron_sdk_py/proto/core/contract/vote_asset_contract_pb2.py
tron_sdk_py/proto/core/contract/vote_asset_contract_pb2_grpc.py
tron_sdk_py/proto/core/contract/witness_contract_pb2.py
tron_sdk_py/proto/core/contract/witness_contract_pb2_grpc.py
tron_sdk_py/types.py
tron_sdk_py-0.3.0.dist-info/METADATA
tron_sdk_py-0.3.0.dist-info/WHEEL
tron_sdk_py-0.3.0.dist-info/RECORD
