Metadata-Version: 2.3
Name: tron_sdk_py
Version: 0.3.0
Summary: TRON-SDK-PY
License: GPL-3.0-only
Author: TRON Devs
Author-email: coredevs@tron.network
Requires-Python: >=3.7,<4.0
Classifier: License :: OSI Approved :: GNU General Public License v3 (GPLv3)
Classifier: Programming Language :: Python :: 3
Classifier: Programming Language :: Python :: 3.7
Classifier: Programming Language :: Python :: 3.8
Classifier: Programming Language :: Python :: 3.9
Classifier: Programming Language :: Python :: 3.10
Classifier: Programming Language :: Python :: 3.11
Classifier: Programming Language :: Python :: 3.12
Classifier: Programming Language :: Python :: 3.13
Requires-Dist: base58 (>=2.0.1,<3.0.0)
Requires-Dist: ecdsa (>=0.16.0,<0.17.0)
Requires-Dist: eth_abi (>=2.1.1,<3.0.0)
Requires-Dist: googleapis-common-protos (>=1.70.0,<2.0.0)
Requires-Dist: grpcio (>=1.31.0,<2.0.0)
Requires-Dist: protobuf (>=3.13.0,<4.0.0)
Requires-Dist: pycryptodome (==3.9.8)
